Metadata-Version: 2.1
Name: github-installer
Version: 0.0.1
Summary: A basic github project installer
Home-page: UNKNOWN
Author: Emrovsky
Author-email: eemrovsky@gmail.com
License: MIT
Keywords: github installer
Platform: UNKNOWN
Classifier: Development Status :: 5 - Production/Stable
Classifier: Intended Audience :: Education
Classifier: Operating System :: Microsoft :: Windows :: Windows 10
Classifier: License :: OSI Approved :: MIT License
Classifier: Programming Language :: Python :: 3
